inventorpy/__init__.py
inventorpy/__main__.py
inventorpy/__version__.py
inventorpy/adapters/__init__.py
inventorpy/adapters/config.py
inventorpy/adapters/emails.py
inventorpy/adapters/orm.py
inventorpy/adapters/views.py
inventorpy/domain/__init__.py
inventorpy/domain/commands.py
inventorpy/domain/emails.py
inventorpy/domain/events.py
inventorpy/domain/models.py
inventorpy/domain/ports.py
inventorpy/services/__init__.py
inventorpy/services/command_handlers.py
inventorpy/services/event_handlers.py
inventorpy-0.1.0a5.dist-info/DESCRIPTION.rst
inventorpy-0.1.0a5.dist-info/METADATA
inventorpy-0.1.0a5.dist-info/RECORD
inventorpy-0.1.0a5.dist-info/WHEEL
inventorpy-0.1.0a5.dist-info/metadata.json
inventorpy-0.1.0a5.dist-info/top_level.txt
