Metadata-Version: 2.0
Name: inventorpy
Version: 0.1.0a5
Summary: An inventory and service management application.
Home-page: https://github.com/J-Kirch/inventorpy
Author: Johnny Kirchman
Author-email: JKirch86@gmail.com
License: MIT
Platform: UNKNOWN
Classifier: Development Status :: 2 - Pre-Alpha
Classifier: Intended Audience :: Developers
Classifier: License :: OSI Approved :: MIT License
Classifier: Natural Language :: English
Classifier: Programming Language :: Python :: 3.6
Requires-Dist: bcrypt
Requires-Dist: flask
Requires-Dist: sqlalchemy
Requires-Dist: sqlalchemy-utils
